Metadata-Version: 2.1
Name: PolynomialRegression
Version: 0.0.1
Summary: A library for polynomial regression
Home-page: UNKNOWN
Author: Sabrina Marshal and Sharon Immanuel
Author-email: sharonimmanuel01@gmail.com
License: MIT
Keywords: polynomial regression,best hypothesis
Platform: UNKNOWN
Classifier: Development Status :: 5 - Production/Stable
Classifier: Intended Audience :: Education
Classifier: Operating System :: Microsoft :: Windows :: Windows 10
Classifier: License :: OSI Approved :: MIT License
Classifier: Programming Language :: Python :: 3
